mongodol/__init__.py
mongodol/add_ons.py
mongodol/base.py
mongodol/constants.py
mongodol/errors.py
mongodol/recipes.py
mongodol/stores.py
mongodol/tracking_methods.py
mongodol/trans.py
mongodol/util.py
mongodol/scrap/__init__.py
mongodol/scrap/old01.py
mongodol/scrap/views_work.py
mongodol/tests/__init__.py
mongodol/tests/add_ons_test.py
mongodol/tests/base_test.py
mongodol/tests/data.py
mongodol/tests/not_working.py
mongodol/tests/stores_test.py
mongodol/tests/util.py
mongodol/tests/int_tests/__init__.py
mongodol/tests/int_tests/base_int_test.py
mongodol/tests/int_tests/conftest.py
mongodol/utils/__init__.py
mongodol/utils/werk_local.py
mongodol-0.0.3.dist-info/LICENSE
mongodol-0.0.3.dist-info/METADATA
mongodol-0.0.3.dist-info/WHEEL
mongodol-0.0.3.dist-info/top_level.txt
mongodol-0.0.3.dist-info/RECORD
