Metadata-Version: 2.1
Name: mongodol
Version: 0.0.3
Summary: MongoDB Data Object Layer
Home-page: https://github.com/i2mint/mongodol
Author: OtoSense
License: apache-2.0
Platform: any
Requires-Dist: pymongo
Requires-Dist: dol
Requires-Dist: linkup
Requires-Dist: i2
